{
    "display": {
        "icon": {
            "nbt": "{CustomModelData:2}",
            "id": "minecraft:carrot_on_a_stick"
        },
        "title": {
            "translate": "pl.adv.arrowpack.title"
        },
        "description": {
            "translate": "pl.adv.arrowpack.description"
        },
        "announce_to_chat": false
    },
    "parent": "pld:experience/job/1/base",
    "criteria": {
        "sword0": {
            "trigger": "minecraft:inventory_changed",
            "conditions": {
                "items": [
                    {
                        "item": "minecraft:carrot_on_a_stick",
                        "nbt": "{id:\"panling:arrowpack\"}"
                    }
                ],
                "player": {
                    "player": {
                        "advancements": {
                            "pld:experience/job/1/base": "true"
                        }
                    }
                }
            }
        }
    },
    "rewards": {
        "function": "pld:adv/gameplay/experience/job/1/arrowpack"
    }
}